smithnormalform/__init__.py
smithnormalform/ed.py
smithnormalform/matrix.py
smithnormalform/pid.py
smithnormalform/snfproblem.py
smithnormalform/z.py
smithnormalform/zi.py
test/__init__.py
test/test_matrix.py
test/test_snfproblem.py
test/test_z.py
test/test_zi.py
smithnormalform-0.6.0.dist-info/LICENSE
smithnormalform-0.6.0.dist-info/METADATA
smithnormalform-0.6.0.dist-info/WHEEL
smithnormalform-0.6.0.dist-info/top_level.txt
smithnormalform-0.6.0.dist-info/RECORD
