Metadata-Version: 2.1
Name: smithnormalform
Version: 0.6.0
Summary: A tool for computing the Smith Normal Forms over arbitrary Principle Ideal Domains
Home-page: https://github.com/corbinmcneill/snf
Author: Corbin McNeill
Author-email: corbin.mc96@gmail.com
License: UNKNOWN
Platform: UNKNOWN
Classifier: Programming Language :: Python :: 3.6
Classifier: Programming Language :: Python :: 3.7
Classifier: Programming Language :: Python :: 3.8
Classifier: Programming Language :: Python :: 3.9
Classifier: Intended Audience :: Science/Research
Classifier: License :: OSI Approved :: GNU General Public License v3 (GPLv3)
Classifier: Natural Language :: English
Classifier: Operating System :: OS Independent
Classifier: Topic :: Scientific/Engineering
Classifier: Topic :: Scientific/Engineering :: Mathematics
Requires-Python: >=3.6
